chipmunk/__init__.py
chipmunk/common/__init__.py
chipmunk/common/geometry/__init__.py
chipmunk/common/geometry/point.py
chipmunk_cad-0.0.1.dist-info/LICENSE
chipmunk_cad-0.0.1.dist-info/METADATA
chipmunk_cad-0.0.1.dist-info/WHEEL
chipmunk_cad-0.0.1.dist-info/top_level.txt
chipmunk_cad-0.0.1.dist-info/RECORD
