Metadata-Version: 2.1
Name: chipmunk-cad
Version: 0.0.1
Summary: A library for designing full-custom IC's
Author-email: Bram Rooseleer <bram.rooseleer@gmail.com>
Project-URL: Homepage, https://github.com/broosele/chipmunk
Project-URL: Bug Tracker, https://github.com/broosele/chipmunk/issues
Classifier: Programming Language :: Python :: 3
Classifier: Operating System :: OS Independent
Requires-Python: >=3.9
License-File: LICENSE
